wsrpc/__init__.py
websocket_rpc-0.0.6.dist-info/LICENSE
websocket_rpc-0.0.6.dist-info/METADATA
websocket_rpc-0.0.6.dist-info/WHEEL
websocket_rpc-0.0.6.dist-info/top_level.txt
websocket_rpc-0.0.6.dist-info/RECORD
