Metadata-Version: 2.1
Name: websocket-rpc
Version: 0.0.6
Summary: msgpack rpc over websocket
Home-page: https://github.com/guyingbo/websocket-rpc
Author: Yingbo Gu
Author-email: tensiongyb@gmail.com
Maintainer: Yingbo Gu
Maintainer-email: tensiongyb@gmail.com
License: MIT
Platform: UNKNOWN
Classifier: License :: OSI Approved :: MIT License
Classifier: Framework :: AsyncIO
Classifier: Intended Audience :: Developers
Classifier: Programming Language :: Python :: 3.6
Classifier: Programming Language :: Python :: 3.7
Classifier: Programming Language :: Python :: 3.8
Requires-Python: >=3.6
Requires-Dist: websockets
Requires-Dist: msgpack (>=1.0.0)
